aiavatar/__init__.py
aiavatar/auth.py
aiavatar/adapter/__init__.py
aiavatar/adapter/base.py
aiavatar/adapter/client.py
aiavatar/adapter/models.py
aiavatar/adapter/http/__init__.py
aiavatar/adapter/http/client.py
aiavatar/adapter/http/server.py
aiavatar/adapter/linebot/__init__.py
aiavatar/adapter/linebot/server.py
aiavatar/adapter/linebot/session_manager/__init__.py
aiavatar/adapter/linebot/session_manager/base.py
aiavatar/adapter/linebot/session_manager/postgres.py
aiavatar/adapter/local/__init__.py
aiavatar/adapter/local/client.py
aiavatar/adapter/local/server.py
aiavatar/adapter/websocket/__init__.py
aiavatar/adapter/websocket/client.py
aiavatar/adapter/websocket/server.py
aiavatar/admin/__init__.py
aiavatar/admin/config.py
aiavatar/admin/control.py
aiavatar/animation/__init__.py
aiavatar/animation/vrchat.py
aiavatar/character/__init__.py
aiavatar/character/binding.py
aiavatar/character/memory.py
aiavatar/character/models.py
aiavatar/character/service.py
aiavatar/character/tools.py
aiavatar/character/repository/__init__.py
aiavatar/character/repository/base.py
aiavatar/character/repository/postgres.py
aiavatar/character/repository/sqlite.py
aiavatar/database/__init__.py
aiavatar/database/base.py
aiavatar/database/postgres.py
aiavatar/device/__init__.py
aiavatar/device/audio.py
aiavatar/device/video.py
aiavatar/eval/__init__.py
aiavatar/eval/dialog.py
aiavatar/face/__init__.py
aiavatar/face/vrchat.py
aiavatar/sts/__init__.py
aiavatar/sts/models.py
aiavatar/sts/pipeline.py
aiavatar/sts/llm/__init__.py
aiavatar/sts/llm/base.py
aiavatar/sts/llm/chatgpt.py
aiavatar/sts/llm/claude.py
aiavatar/sts/llm/dify.py
aiavatar/sts/llm/gemini.py
aiavatar/sts/llm/litellm.py
aiavatar/sts/llm/context_manager/__init__.py
aiavatar/sts/llm/context_manager/base.py
aiavatar/sts/llm/context_manager/postgres.py
aiavatar/sts/llm/tools/__init__.py
aiavatar/sts/llm/tools/gemini_websearch.py
aiavatar/sts/llm/tools/grok_search.py
aiavatar/sts/llm/tools/mcp.py
aiavatar-0.8.5.dist-info/LICENSE
aiavatar-0.8.5.dist-info/METADATA
aiavatar-0.8.5.dist-info/WHEEL
aiavatar-0.8.5.dist-info/top_level.txt
aiavatar-0.8.5.dist-info/RECORD
