Metadata-Version: 2.1
Name: aiavatar
Version: 0.8.5
Summary: 🥰 Building AI-based conversational avatars lightning fast ⚡️💬
Home-page: https://github.com/uezo/aiavatar
Author: uezo
Author-email: uezo@uezo.net
Maintainer: uezo
Maintainer-email: uezo@uezo.net
License: Apache v2
Classifier: Programming Language :: Python :: 3
License-File: LICENSE
Requires-Dist: httpx>=0.27.0
Requires-Dist: openai>=1.55.3
Requires-Dist: aiofiles>=24.1.0
Requires-Dist: numpy>=2.2.3
Requires-Dist: PyAudio>=0.2.14
Requires-Dist: silero-vad>=6.0.0
